discord/wrapper/__init__.py
discord/wrapper/author.py
discord/wrapper/bot.py
discord/wrapper/channel.py
discord/wrapper/content.py
discord/wrapper/embed.py
discord/wrapper/events.py
discord/wrapper/exceptions.py
discord/wrapper/gateway.py
discord/wrapper/guild.py
discord/wrapper/http_client.py
discord/wrapper/intents.py
discord/wrapper/message.py
discord/wrapper/user.py
discord.wrapper-3.0.3.dist-info/METADATA
discord.wrapper-3.0.3.dist-info/WHEEL
discord.wrapper-3.0.3.dist-info/top_level.txt
discord.wrapper-3.0.3.dist-info/RECORD
