Metadata-Version: 2.1
Name: discord.wrapper
Version: 3.0.3
Summary: An API wrapper for discord.
Home-page: https://github.com/FrostiiWeeb/discord.wrapper
Author: Alex Hutz
Author-email: frostiiweeb@gmail.com
License: MIT
Project-URL: Documentation, https://discordwrapper.readthedocs.io/en/latest
Project-URL: Issue Tracker, https://github.com/FrostiiWeeb/discord.wrapper/issues
Keywords: discord
Platform: UNKNOWN
Classifier: Development Status :: 3 - Alpha
Classifier: Intended Audience :: Developers
Classifier: Topic :: Utilities
Classifier: License :: OSI Approved :: MIT License
Classifier: Programming Language :: Python :: 3.7
Classifier: Programming Language :: Python :: 3.8
Classifier: Programming Language :: Python :: 3.9
Requires-Python: >=3.7.0
Requires-Dist: aiohttp (>=3.7.3)
Requires-Dist: uvloop
